<Goal>
  <Highlights>
    <League>Eerste Divisie</League>
    <StartDate>October 23, 2015</StartDate>
    <StartTime>• 19:00</StartTime>
    <Stadium>• TATA Steel Stadion</Stadium>
    <City>Velsen-Zuid</City>
    <Referee>S. Berben</Referee>
    <Attendees>1831</Attendees>
    <FullTime>FT</FullTime>
    <ExtraInformation></ExtraInformation>
    <FullTimeScore>3-0</FullTimeScore>
    <Home>
      <Team>Telstar</Team>
      <GoalScorersList>
        <Goal GoalId="1" Minute="45" PlayerLink="http://www.goal.com/en/people/bosnia-and-herzegovina/82221/marko-maleti%C4%87" OwnGoal="n">M. Maletić</Goal>
        <Goal GoalId="2" Minute="88" PlayerLink="http://www.goal.com/en/people/netherlands/84482/tarik-tissoudali" OwnGoal="n">T. Tissoudali</Goal>
        <Goal GoalId="3" Minute="90" PlayerLink="http://www.goal.com/en/people/netherlands/84482/tarik-tissoudali" OwnGoal="n">T. Tissoudali</Goal>
      </GoalScorersList>
      <FinalGoals>3</FinalGoals>
    </Home>
    <Away>
      <Team>Achilles '29</Team>
      <GoalScorersList/>
      <FinalGoals>0</FinalGoals>
    </Away>
  </Highlights>
  <Events>
    <AssistList/>
    <GoalList>
      <Goal GoalId="1" Minute="88">Tarik Tissoudali</Goal>
      <Goal GoalId="2" Minute="90">Tarik Tissoudali</Goal>
    </GoalList>
    <MissedPenaltyList/>
    <PenaltyGoalList>
      <PenaltyGoal PenaltyGoalId="1" Minute="451">Marko Maletić</PenaltyGoal>
    </PenaltyGoalList>
    <RedCardList/>
    <YellowCardList>
      <YellowCard YellowCardId="1" Minute="45+2">Jop van Steen</YellowCard>
      <YellowCard YellowCardId="2" Minute="74">Mehmet Dingil</YellowCard>
      <YellowCard YellowCardId="3" Minute="90">Fabian Serrarens</YellowCard>
    </YellowCardList>
    <YellowRedList/>
    <OwnGoalList/>
    <SubstitutionList>
      <Substitution SubstitutionId="1" Minute="46" SubOut="Hielke Penterman" SubIn="Thijs Hendriks"/>
      <Substitution SubstitutionId="2" Minute="64" SubOut="Joey Dekkers" SubIn="Daniel van Straaten"/>
      <Substitution SubstitutionId="3" Minute="65" SubOut="Marko Maletić" SubIn="شيت Schet"/>
      <Substitution SubstitutionId="4" Minute="79" SubOut="Kenny Elders" SubIn="Omid Popalzay"/>
    </SubstitutionList>
  </Events>
  <LastGame>
    <Home>
      <LastGameLeague>Eerste Divisie</LastGameLeague>
      <DateLastGame>October 16, 2015</DateLastGame>
      <OpponentLastGame>VVV Venlo</OpponentLastGame>
      <ResultLastGame CurrentTeamGoals="2" OpponentGoals="1">1-2</ResultLastGame>
      <HomeAwayLastGame>away</HomeAwayLastGame>
      <WinDrawLostLastGame>won</WinDrawLostLastGame>
      <GoneFromLineUpList>
        <Player PlayerId="1">S. Lilipaly</Player>
      </GoneFromLineUpList>
      <NewInLineUpList>
        <Player PlayerId="1">T. Keurntjes</Player>
      </NewInLineUpList>
    </Home>
    <Away>
      <LastGameLeague>Eerste Divisie</LastGameLeague>
      <DateLastGame>October 18, 2015</DateLastGame>
      <OpponentLastGame>NAC Breda</OpponentLastGame>
      <ResultLastGame CurrentTeamGoals="1" OpponentGoals="2">1-2</ResultLastGame>
      <HomeAwayLastGame>home</HomeAwayLastGame>
      <WinDrawLostLastGame>lost</WinDrawLostLastGame>
      <GoneFromLineUpList>
        <Player PlayerId="1">B. Beijer</Player>
      </GoneFromLineUpList>
      <NewInLineUpList>
        <Player PlayerId="1">D. Ramezani</Player>
      </NewInLineUpList>
    </Away>
  </LastGame>
  <Lineups>
    <Home>
      <Player PlayerId="1">
        <Name>Wesley Zonneveld</Name>
        <Fullname>Wesley Zonneveld</Fullname>
        <Nickname></Nickname>
        <BirthDate>June 17, 1992</BirthDate>
        <BirthPlace City="Haarlem" Country="Netherlands"/>
        <Height>1.95</Height>
        <Weight></Weight>
        <WikiPosition>Goalkeeper</WikiPosition>
        <GoalComPosition></GoalComPosition>
        <GoalComPlayerNumber>20</GoalComPlayerNumber>
        <GoalComShownName>W. Zonneveld</GoalComShownName>
        <GoalComWebsite>http://www.goal.com/en/people/netherlands/49114/wesley-zonneveld</GoalComWebsite>
        <YouthClubs>
          <YouthClub YouthClubId="1" Years="">FC Lisse</YouthClub>
          <YouthClub YouthClubId="2" Years="">AZ</YouthClub>
        </YouthClubs>
        <SeniorClubs>
          <SeniorClub SeniorClubId="1" Years="2011-" Caps="56" Goals="0">Telstar</SeniorClub>
        </SeniorClubs>
        <NationalTeams/>
        <CurrentTeam>Telstar</CurrentTeam>
        <CurrentNumber>20</CurrentNumber>
      </Player>
      <Player PlayerId="2">
        <Name>Jordi Tutuarima</Name>
        <Fullname></Fullname>
        <Nickname></Nickname>
        <BirthDate>April 28, 1993</BirthDate>
        <BirthPlace City="" Country=""/>
        <Height></Height>
        <Weight></Weight>
        <WikiPosition>Midfielder</WikiPosition>
        <GoalComPosition></GoalComPosition>
        <GoalComPlayerNumber>15</GoalComPlayerNumber>
        <GoalComShownName>J. Tutuarima</GoalComShownName>
        <GoalComWebsite>http://www.goal.com/en/people/netherlands/78161/jordi-tutuarima</GoalComWebsite>
        <YouthClubs/>
        <SeniorClubs/>
        <NationalTeams/>
        <CurrentTeam></CurrentTeam>
        <CurrentNumber></CurrentNumber>
      </Player>
      <Player PlayerId="3">
        <Name>Frank Korpershoek</Name>
        <Fullname>Frank Korpershoek</Fullname>
        <Nickname></Nickname>
        <BirthDate>October 29, 1984</BirthDate>
        <BirthPlace City="Heemstede" Country="Netherlands"/>
        <Height>1.79</Height>
        <Weight></Weight>
        <WikiPosition>Midfielder</WikiPosition>
        <GoalComPosition></GoalComPosition>
        <GoalComPlayerNumber>6</GoalComPlayerNumber>
        <GoalComShownName>F. Korpershoek</GoalComShownName>
        <GoalComWebsite>http://www.goal.com/en/people/netherlands/19611/frank-korpershoek</GoalComWebsite>
        <YouthClubs>
          <YouthClub YouthClubId="1" Years="">HFC</YouthClub>
          <YouthClub YouthClubId="2" Years="">DWV</YouthClub>
        </YouthClubs>
        <SeniorClubs>
          <SeniorClub SeniorClubId="1" Years="2006-" Caps="249" Goals="9">Telstar</SeniorClub>
        </SeniorClubs>
        <NationalTeams/>
        <CurrentTeam>Telstar</CurrentTeam>
        <CurrentNumber>6</CurrentNumber>
      </Player>
      <Player PlayerId="4">
        <Name>Crescendo van Berkel</Name>
        <Fullname>Crescendo van Berkel</Fullname>
        <Nickname></Nickname>
        <BirthDate>April 06, 1992</BirthDate>
        <BirthPlace City="The Hague" Country="Netherlands"/>
        <Height>1.83</Height>
        <Weight></Weight>
        <WikiPosition>Centre back</WikiPosition>
        <GoalComPosition></GoalComPosition>
        <GoalComPlayerNumber>23</GoalComPlayerNumber>
        <GoalComShownName>C. van Berkel</GoalComShownName>
        <GoalComWebsite>http://www.goal.com/en/people/netherlands/60293/crescendo-van-berkel</GoalComWebsite>
        <YouthClubs>
          <YouthClub YouthClubId="1" Years="">Quick</YouthClub>
          <YouthClub YouthClubId="2" Years="2011-2012">Sparta Rotterdam</YouthClub>
        </YouthClubs>
        <SeniorClubs>
          <SeniorClub SeniorClubId="1" Years="2012-2014" Caps="30" Goals="1">Sparta</SeniorClub>
          <SeniorClub SeniorClubId="2" Years="2014-2015" Caps="10" Goals="0">Roda JC</SeniorClub>
          <SeniorClub SeniorClubId="3" Years="2015-" Caps="26" Goals="1">Telstar</SeniorClub>
        </SeniorClubs>
        <NationalTeams/>
        <CurrentTeam>Telstar</CurrentTeam>
        <CurrentNumber>23</CurrentNumber>
      </Player>
      <Player PlayerId="5">
        <Name>Stefano Lilipaly</Name>
        <Fullname>Stefano Jantje Lilipaly</Fullname>
        <Nickname></Nickname>
        <BirthDate>January 10, 1990</BirthDate>
        <BirthPlace City="Arnhem" Country="Netherlands"/>
        <Height>1.75</Height>
        <Weight></Weight>
        <WikiPosition>Attacking midfielder, Winger</WikiPosition>
        <GoalComPosition></GoalComPosition>
        <GoalComPlayerNumber>26</GoalComPlayerNumber>
        <GoalComShownName>S. Lilipaly</GoalComShownName>
        <GoalComWebsite>http://www.goal.com/en/people/netherlands/43279/stefano-lilipaly</GoalComWebsite>
        <YouthClubs>
          <YouthClub YouthClubId="1" Years="1997-2000">DCG</YouthClub>
          <YouthClub YouthClubId="2" Years="2000-2001">AZ</YouthClub>
          <YouthClub YouthClubId="3" Years="2001-2010">Utrecht</YouthClub>
        </YouthClubs>
        <SeniorClubs>
          <SeniorClub SeniorClubId="1" Years="2010-2012" Caps="5" Goals="1">Utrecht</SeniorClub>
          <SeniorClub SeniorClubId="2" Years="2012-2014" Caps="39" Goals="3">Almere City</SeniorClub>
          <SeniorClub SeniorClubId="3" Years="2014" Caps="0" Goals="0">Consadole Sapporo</SeniorClub>
          <SeniorClub SeniorClubId="4" Years="2015-2017" Caps="44" Goals="9">Telstar</SeniorClub>
          <SeniorClub SeniorClubId="5" Years="2017-" Caps="16" Goals="11">Cambuur</SeniorClub>
        </SeniorClubs>
        <NationalTeams>
          <NationalTeam NationalTeamId="1" Years="2005" Caps="0" Goals="0">Netherlands U-16</NationalTeam>
          <NationalTeam NationalTeamId="2" Years="2007" Caps="0" Goals="0">Netherlands U-17</NationalTeam>
          <NationalTeam NationalTeamId="3" Years="2013-" Caps="9" Goals="2">Indonesia</NationalTeam>
        </NationalTeams>
        <CurrentTeam>Cambuur</CurrentTeam>
        <CurrentNumber>8</CurrentNumber>
      </Player>
      <Player PlayerId="6">
        <Name>Thomas van den Houten</Name>
        <Fullname></Fullname>
        <Nickname></Nickname>
        <BirthDate>July 20, 1990</BirthDate>
        <BirthPlace City="Goes" Country="Netherlands"/>
        <Height>1.80</Height>
        <Weight></Weight>
        <WikiPosition>Defender</WikiPosition>
        <GoalComPosition></GoalComPosition>
        <GoalComPlayerNumber>5</GoalComPlayerNumber>
        <GoalComShownName>T. van den Houten</GoalComShownName>
        <GoalComWebsite>http://www.goal.com/en/people/netherlands/35297/thomas-van-den-houten</GoalComWebsite>
        <YouthClubs>
          <YouthClub YouthClubId="1" Years="">VV Kloetinge</YouthClub>
          <YouthClub YouthClubId="2" Years="{{0|0000}}-2010">RBC</YouthClub>
        </YouthClubs>
        <SeniorClubs>
          <SeniorClub SeniorClubId="1" Years="2010-2011" Caps="12" Goals="0">Olympic Charleroi</SeniorClub>
          <SeniorClub SeniorClubId="2" Years="2011-2012" Caps="" Goals="">VV Goes</SeniorClub>
          <SeniorClub SeniorClubId="3" Years="2012-2015" Caps="" Goals="">HSV Hoek</SeniorClub>
          <SeniorClub SeniorClubId="4" Years="2015-" Caps="42" Goals="0">SC Telstar</SeniorClub>
        </SeniorClubs>
        <NationalTeams/>
        <CurrentTeam>SC Telstar</CurrentTeam>
        <CurrentNumber>5</CurrentNumber>
      </Player>
      <Player PlayerId="7">
        <Name>Kevin van Essen</Name>
        <Fullname>Kevin van Essen</Fullname>
        <Nickname></Nickname>
        <BirthDate>August 18, 1989</BirthDate>
        <BirthPlace City="Naarden" Country="Netherlands"/>
        <Height>1.75</Height>
        <Weight></Weight>
        <WikiPosition>Midfielder</WikiPosition>
        <GoalComPosition></GoalComPosition>
        <GoalComPlayerNumber>12</GoalComPlayerNumber>
        <GoalComShownName>K. van Essen</GoalComShownName>
        <GoalComWebsite>http://www.goal.com/en/people/netherlands/22890/kevin-van-essen</GoalComWebsite>
        <YouthClubs>
          <YouthClub YouthClubId="1" Years="">SV Almere</YouthClub>
          <YouthClub YouthClubId="2" Years="">FC Omniworld</YouthClub>
        </YouthClubs>
        <SeniorClubs>
          <SeniorClub SeniorClubId="1" Years="2007-2010" Caps="8" Goals="0">FC Omniworld</SeniorClub>
          <SeniorClub SeniorClubId="2" Years="2010-2012" Caps="53" Goals="7">Argon</SeniorClub>
          <SeniorClub SeniorClubId="3" Years="2012-2016" Caps="108" Goals="11">Telstar</SeniorClub>
        </SeniorClubs>
        <NationalTeams/>
        <CurrentTeam>free agent</CurrentTeam>
        <CurrentNumber></CurrentNumber>
      </Player>
      <Player PlayerId="8">
        <Name>Edo Knol</Name>
        <Fullname>Edo Knol</Fullname>
        <Nickname></Nickname>
        <BirthDate>July 13, 1995</BirthDate>
        <BirthPlace City="Velserbroek" Country="Netherlands"/>
        <Height>1.76</Height>
        <Weight></Weight>
        <WikiPosition>Midfielder</WikiPosition>
        <GoalComPosition></GoalComPosition>
        <GoalComPlayerNumber>18</GoalComPlayerNumber>
        <GoalComShownName>E. Knol</GoalComShownName>
        <GoalComWebsite>http://www.goal.com/en/people/netherlands/173472/edo-knol</GoalComWebsite>
        <YouthClubs>
          <YouthClub YouthClubId="1" Years="">VSV</YouthClub>
          <YouthClub YouthClubId="2" Years="">Haarlem</YouthClub>
          <YouthClub YouthClubId="3" Years="">HFC EDO</YouthClub>
          <YouthClub YouthClubId="4" Years="">ADO Den Haag</YouthClub>
        </YouthClubs>
        <SeniorClubs>
          <SeniorClub SeniorClubId="1" Years="2014-" Caps="54" Goals="2">Telstar</SeniorClub>
        </SeniorClubs>
        <NationalTeams/>
        <CurrentTeam>Telstar</CurrentTeam>
        <CurrentNumber>18</CurrentNumber>
      </Player>
      <Player PlayerId="9">
        <Name>Marko Maletić</Name>
        <Fullname>Marko Maletić</Fullname>
        <Nickname></Nickname>
        <BirthDate>October 25, 1993</BirthDate>
        <BirthPlace City="Belgrade" Country="SFR Yugoslavia"/>
        <Height>1.96</Height>
        <Weight></Weight>
        <WikiPosition>Striker</WikiPosition>
        <GoalComPosition></GoalComPosition>
        <GoalComPlayerNumber>9</GoalComPlayerNumber>
        <GoalComShownName>M. Maletić</GoalComShownName>
        <GoalComWebsite>http://www.goal.com/en/people/bosnia-and-herzegovina/82221/marko-maleti%C4%87</GoalComWebsite>
        <YouthClubs>
          <YouthClub YouthClubId="1" Years="{{0|0000}}-2004">Voetbalvereniging Lengel</YouthClub>
          <YouthClub YouthClubId="2" Years="2004-2009">De Graafschap</YouthClub>
          <YouthClub YouthClubId="3" Years="2010-2012">Utrecht</YouthClub>
        </YouthClubs>
        <SeniorClubs>
          <SeniorClub SeniorClubId="1" Years="2012-2014" Caps="14" Goals="1">VfB Stuttgart II</SeniorClub>
          <SeniorClub SeniorClubId="2" Years="2013-2014" Caps="29" Goals="8">→ FC Oss (loan)</SeniorClub>
          <SeniorClub SeniorClubId="3" Years="2014-2016" Caps="6" Goals="0">Excelsior</SeniorClub>
          <SeniorClub SeniorClubId="4" Years="2015-2016" Caps="27" Goals="9">→ Telstar (loan)</SeniorClub>
          <SeniorClub SeniorClubId="5" Years="2016-" Caps="0" Goals="0">Lommel United</SeniorClub>
        </SeniorClubs>
        <NationalTeams>
          <NationalTeam NationalTeamId="1" Years="2009-2010" Caps="9" Goals="2">Bosnia and Herzegovina U17</NationalTeam>
          <NationalTeam NationalTeamId="2" Years="2011-2012" Caps="8" Goals="3">Bosnia and Herzegovina U19</NationalTeam>
          <NationalTeam NationalTeamId="3" Years="2012-2014" Caps="11" Goals="2">Bosnia and Herzegovina U21</NationalTeam>
        </NationalTeams>
        <CurrentTeam>Lommel United</CurrentTeam>
        <CurrentNumber>25</CurrentNumber>
      </Player>
      <Player PlayerId="10">
        <Name>Fabian Serrarens</Name>
        <Fullname>Fabian Serrarens</Fullname>
        <Nickname></Nickname>
        <BirthDate>February 09, 1991</BirthDate>
        <BirthPlace City="Amsterdam" Country="Netherlands"/>
        <Height>1.93</Height>
        <Weight></Weight>
        <WikiPosition>Striker</WikiPosition>
        <GoalComPosition></GoalComPosition>
        <GoalComPlayerNumber>7</GoalComPlayerNumber>
        <GoalComShownName>F. Serrarens</GoalComShownName>
        <GoalComWebsite>http://www.goal.com/en/people/netherlands/57537/fabian-serrarens</GoalComWebsite>
        <YouthClubs>
          <YouthClub YouthClubId="1" Years="">SC Voorland</YouthClub>
          <YouthClub YouthClubId="2" Years="">FC Utrecht</YouthClub>
          <YouthClub YouthClubId="3" Years="">IJVV Stormvogels</YouthClub>
          <YouthClub YouthClubId="4" Years="">Zeeburgia</YouthClub>
          <YouthClub YouthClubId="5" Years="">Ajax</YouthClub>
          <YouthClub YouthClubId="6" Years="">NAC Breda</YouthClub>
        </YouthClubs>
        <SeniorClubs>
          <SeniorClub SeniorClubId="1" Years="2011-2015" Caps="91" Goals="22">Almere City</SeniorClub>
          <SeniorClub SeniorClubId="2" Years="2015-" Caps="34" Goals="7">Telstar</SeniorClub>
        </SeniorClubs>
        <NationalTeams/>
        <CurrentTeam>Telstar</CurrentTeam>
        <CurrentNumber>7</CurrentNumber>
      </Player>
      <Player PlayerId="11">
        <Name>Tarik Tissoudali</Name>
        <Fullname>Tarik Tissoudali</Fullname>
        <Nickname></Nickname>
        <BirthDate>April 02, 1993</BirthDate>
        <BirthPlace City="Amsterdam" Country="Netherlands"/>
        <Height>1.75</Height>
        <Weight></Weight>
        <WikiPosition>Winger</WikiPosition>
        <GoalComPosition></GoalComPosition>
        <GoalComPlayerNumber>17</GoalComPlayerNumber>
        <GoalComShownName>T. Tissoudali</GoalComShownName>
        <GoalComWebsite>http://www.goal.com/en/people/netherlands/84482/tarik-tissoudali</GoalComWebsite>
        <YouthClubs>
          <YouthClub YouthClubId="1" Years="">Argon</YouthClub>
          <YouthClub YouthClubId="2" Years="">Young Boys</YouthClub>
          <YouthClub YouthClubId="3" Years="">DWS</YouthClub>
          <YouthClub YouthClubId="4" Years="">Sparta Nijkerk</YouthClub>
        </YouthClubs>
        <SeniorClubs>
          <SeniorClub SeniorClubId="1" Years="2014-2016" Caps="74" Goals="23">Telstar</SeniorClub>
          <SeniorClub SeniorClubId="2" Years="2016-" Caps="0" Goals="0">Le Havre</SeniorClub>
          <SeniorClub SeniorClubId="3" Years="2017-" Caps="0" Goals="0">→ SC Cambuur (loan)</SeniorClub>
        </SeniorClubs>
        <NationalTeams>
          <NationalTeam NationalTeamId="1" Years="2016-" Caps="1" Goals="1">Morocco U23</NationalTeam>
        </NationalTeams>
        <CurrentTeam>SC Cambuur</CurrentTeam>
        <CurrentNumber>11</CurrentNumber>
      </Player>
    </Home>
    <Away>
      <Player PlayerId="1">
        <Name>Leon ter Wielen</Name>
        <Fullname>Leon ter Wielen</Fullname>
        <Nickname></Nickname>
        <BirthDate>August 31, 1988</BirthDate>
        <BirthPlace City="Raalte" Country="Netherlands"/>
        <Height>1.95</Height>
        <Weight></Weight>
        <WikiPosition>Goalkeeper</WikiPosition>
        <GoalComPosition></GoalComPosition>
        <GoalComPlayerNumber>1</GoalComPlayerNumber>
        <GoalComShownName>L. ter Wielen</GoalComShownName>
        <GoalComWebsite>http://www.goal.com/en/people/netherlands/33362/leon-ter-wielen</GoalComWebsite>
        <YouthClubs>
          <YouthClub YouthClubId="1" Years="">ROHDA Raalte</YouthClub>
          <YouthClub YouthClubId="2" Years="">OZC</YouthClub>
          <YouthClub YouthClubId="3" Years="">FC Groningen</YouthClub>
        </YouthClubs>
        <SeniorClubs>
          <SeniorClub SeniorClubId="1" Years="2010" Caps="0" Goals="0">BV Veendam</SeniorClub>
          <SeniorClub SeniorClubId="2" Years="2010-2014" Caps="20" Goals="0">PEC Zwolle</SeniorClub>
          <SeniorClub SeniorClubId="3" Years="2014-2016" Caps="73" Goals="0">Achilles '29</SeniorClub>
          <SeniorClub SeniorClubId="4" Years="2016-" Caps="0" Goals="0">Fortuna Sittard</SeniorClub>
        </SeniorClubs>
        <NationalTeams/>
        <CurrentTeam>Fortuna Sittard</CurrentTeam>
        <CurrentNumber>1</CurrentNumber>
      </Player>
      <Player PlayerId="2">
        <Name>Mehmet Dingil</Name>
        <Fullname>Mehmet Dingil</Fullname>
        <Nickname></Nickname>
        <BirthDate>November 28, 1989</BirthDate>
        <BirthPlace City="Veghel" Country="Netherlands"/>
        <Height>1.80</Height>
        <Weight></Weight>
        <WikiPosition>Centre Back</WikiPosition>
        <GoalComPosition></GoalComPosition>
        <GoalComPlayerNumber>4</GoalComPlayerNumber>
        <GoalComShownName>M. Dingil</GoalComShownName>
        <GoalComWebsite>http://www.goal.com/en/people/netherlands/80821/mehmet-dingil</GoalComWebsite>
        <YouthClubs/>
        <SeniorClubs>
          <SeniorClub SeniorClubId="1" Years="-2012" Caps="" Goals="">Blauw Geel '38</SeniorClub>
          <SeniorClub SeniorClubId="2" Years="2012-2014" Caps="48" Goals="8">JVC Cuijk</SeniorClub>
          <SeniorClub SeniorClubId="3" Years="2014-2016" Caps="63" Goals="5">Achilles '29</SeniorClub>
        </SeniorClubs>
        <NationalTeams/>
        <CurrentTeam>free agent</CurrentTeam>
        <CurrentNumber></CurrentNumber>
      </Player>
      <Player PlayerId="3">
        <Name>Migiel Zeller</Name>
        <Fullname></Fullname>
        <Nickname></Nickname>
        <BirthDate>April 08, 1993</BirthDate>
        <BirthPlace City="" Country=""/>
        <Height></Height>
        <Weight></Weight>
        <WikiPosition>Defender</WikiPosition>
        <GoalComPosition></GoalComPosition>
        <GoalComPlayerNumber>21</GoalComPlayerNumber>
        <GoalComShownName>M. Zeller</GoalComShownName>
        <GoalComWebsite>http://www.goal.com/en/people/netherlands/100816/migiel-zeller</GoalComWebsite>
        <YouthClubs/>
        <SeniorClubs/>
        <NationalTeams/>
        <CurrentTeam></CurrentTeam>
        <CurrentNumber></CurrentNumber>
      </Player>
      <Player PlayerId="4">
        <Name>Kenny Elders</Name>
        <Fullname></Fullname>
        <Nickname></Nickname>
        <BirthDate>February 01, 1995</BirthDate>
        <BirthPlace City="Boxmeer" Country="Netherlands"/>
        <Height>1.75</Height>
        <Weight></Weight>
        <WikiPosition>Defender</WikiPosition>
        <GoalComPosition></GoalComPosition>
        <GoalComPlayerNumber>5</GoalComPlayerNumber>
        <GoalComShownName>K. Elders</GoalComShownName>
        <GoalComWebsite>http://www.goal.com/en/people/netherlands/171692/kenny-elders</GoalComWebsite>
        <YouthClubs>
          <YouthClub YouthClubId="1" Years="{{0|0000}}-2005">Vitesse '08</YouthClub>
          <YouthClub YouthClubId="2" Years="2005-2009">N.E.C.</YouthClub>
          <YouthClub YouthClubId="3" Years="2009-2014">N.E.C./FC Oss</YouthClub>
        </YouthClubs>
        <SeniorClubs>
          <SeniorClub SeniorClubId="1" Years="2014-2015" Caps="0" Goals="0">N.E.C.</SeniorClub>
          <SeniorClub SeniorClubId="2" Years="2015-" Caps="30" Goals="0">Achilles '29</SeniorClub>
        </SeniorClubs>
        <NationalTeams/>
        <CurrentTeam>Achilles '29</CurrentTeam>
        <CurrentNumber>5</CurrentNumber>
      </Player>
      <Player PlayerId="5">
        <Name>Barry Beijer</Name>
        <Fullname></Fullname>
        <Nickname></Nickname>
        <BirthDate>December 06, 1989</BirthDate>
        <BirthPlace City="Zevenaar" Country="Netherlands"/>
        <Height>1.84</Height>
        <Weight></Weight>
        <WikiPosition>Defender</WikiPosition>
        <GoalComPosition></GoalComPosition>
        <GoalComPlayerNumber>3</GoalComPlayerNumber>
        <GoalComShownName>B. Beijer</GoalComShownName>
        <GoalComWebsite>http://www.goal.com/en/people/netherlands/80443/barry-beijer</GoalComWebsite>
        <YouthClubs>
          <YouthClub YouthClubId="1" Years="{{0|0000}}-2009">DVV Duiven</YouthClub>
          <YouthClub YouthClubId="2" Years="2009-2011">SBV Vitesse/AGOVV Apeldoorn</YouthClub>
        </YouthClubs>
        <SeniorClubs>
          <SeniorClub SeniorClubId="1" Years="2011-2015" Caps="105" Goals="3">De Treffers</SeniorClub>
          <SeniorClub SeniorClubId="2" Years="2015-" Caps="53" Goals="2">Achilles '29</SeniorClub>
        </SeniorClubs>
        <NationalTeams/>
        <CurrentTeam>Achilles '29</CurrentTeam>
        <CurrentNumber>3</CurrentNumber>
      </Player>
      <Player PlayerId="6">
        <Name>Joey Dekkers</Name>
        <Fullname></Fullname>
        <Nickname></Nickname>
        <BirthDate>October 03, 1989</BirthDate>
        <BirthPlace City="Tegelen" Country="Netherlands"/>
        <Height>1.77</Height>
        <Weight></Weight>
        <WikiPosition>Midfielder</WikiPosition>
        <GoalComPosition></GoalComPosition>
        <GoalComPlayerNumber>14</GoalComPlayerNumber>
        <GoalComShownName>J. Dekkers</GoalComShownName>
        <GoalComWebsite>http://www.goal.com/en/people/netherlands/80909/joey-dekkers</GoalComWebsite>
        <YouthClubs>
          <YouthClub YouthClubId="1" Years="">SC Irene</YouthClub>
        </YouthClubs>
        <SeniorClubs>
          <SeniorClub SeniorClubId="1" Years="{{0|0000}}-2011" Caps="" Goals="">SC Irene</SeniorClub>
          <SeniorClub SeniorClubId="2" Years="2011-2012" Caps="" Goals="">SVC 2000</SeniorClub>
          <SeniorClub SeniorClubId="3" Years="2012-2015" Caps="85" Goals="0">EVV</SeniorClub>
          <SeniorClub SeniorClubId="4" Years="2015-" Caps="53" Goals="1">Achilles '29</SeniorClub>
        </SeniorClubs>
        <NationalTeams/>
        <CurrentTeam>Achilles '29</CurrentTeam>
        <CurrentNumber>14</CurrentNumber>
      </Player>
      <Player PlayerId="7">
        <Name>Jop van Steen</Name>
        <Fullname></Fullname>
        <Nickname></Nickname>
        <BirthDate>December 21, 1984</BirthDate>
        <BirthPlace City="Nijmegen" Country="Netherlands"/>
        <Height>1.80</Height>
        <Weight></Weight>
        <WikiPosition>Midfielder</WikiPosition>
        <GoalComPosition></GoalComPosition>
        <GoalComPlayerNumber>13</GoalComPlayerNumber>
        <GoalComShownName>J. van Steen</GoalComShownName>
        <GoalComWebsite>http://www.goal.com/en/people/netherlands/100815/jop-van-steen</GoalComWebsite>
        <YouthClubs>
          <YouthClub YouthClubId="1" Years="">VV Union</YouthClub>
          <YouthClub YouthClubId="2" Years="">Quick 1888</YouthClub>
        </YouthClubs>
        <SeniorClubs>
          <SeniorClub SeniorClubId="1" Years="{{0|0000}}-2006" Caps="" Goals="">Quick 1888</SeniorClub>
          <SeniorClub SeniorClubId="2" Years="2006-2010" Caps="" Goals="">RKHVV</SeniorClub>
          <SeniorClub SeniorClubId="3" Years="2010-2011" Caps="" Goals="">Juliana '31</SeniorClub>
          <SeniorClub SeniorClubId="4" Years="2011-2013" Caps="" Goals="">RKHVV</SeniorClub>
          <SeniorClub SeniorClubId="5" Years="2013-" Caps="129" Goals="8">Achilles '29</SeniorClub>
        </SeniorClubs>
        <NationalTeams/>
        <CurrentTeam>Achilles '29</CurrentTeam>
        <CurrentNumber>13</CurrentNumber>
      </Player>
      <Player PlayerId="8">
        <Name>Boy van de Beek</Name>
        <Fullname></Fullname>
        <Nickname></Nickname>
        <BirthDate>November 13, 1993</BirthDate>
        <BirthPlace City="Nijmegen" Country="Netherlands"/>
        <Height>1.85</Height>
        <Weight></Weight>
        <WikiPosition>Midfielder</WikiPosition>
        <GoalComPosition></GoalComPosition>
        <GoalComPlayerNumber>18</GoalComPlayerNumber>
        <GoalComShownName>B. van de Beek</GoalComShownName>
        <GoalComWebsite>http://www.goal.com/en/people/netherlands/202262/boy-van-de-beek</GoalComWebsite>
        <YouthClubs>
          <YouthClub YouthClubId="1" Years="1998-2000">SV Blauw Wit</YouthClub>
          <YouthClub YouthClubId="2" Years="2000-2009">N.E.C.</YouthClub>
          <YouthClub YouthClubId="3" Years="2009-2011">N.E.C./FC Oss</YouthClub>
        </YouthClubs>
        <SeniorClubs>
          <SeniorClub SeniorClubId="1" Years="2011-2014" Caps="" Goals="">VV Germania</SeniorClub>
          <SeniorClub SeniorClubId="2" Years="2014-2015" Caps="" Goals="">VV Alverna</SeniorClub>
          <SeniorClub SeniorClubId="3" Years="2015-" Caps="58" Goals="5">Achilles '29</SeniorClub>
        </SeniorClubs>
        <NationalTeams/>
        <CurrentTeam>Achilles '29</CurrentTeam>
        <CurrentNumber>7</CurrentNumber>
      </Player>
      <Player PlayerId="9">
        <Name>Hielke Penterman</Name>
        <Fullname></Fullname>
        <Nickname></Nickname>
        <BirthDate>January 05, 1986</BirthDate>
        <BirthPlace City="" Country=""/>
        <Height></Height>
        <Weight></Weight>
        <WikiPosition>Midfielder</WikiPosition>
        <GoalComPosition></GoalComPosition>
        <GoalComPlayerNumber>11</GoalComPlayerNumber>
        <GoalComShownName>H. Penterman</GoalComShownName>
        <GoalComWebsite>http://www.goal.com/en/people/netherlands/60142/hielke-penterman</GoalComWebsite>
        <YouthClubs/>
        <SeniorClubs/>
        <NationalTeams/>
        <CurrentTeam></CurrentTeam>
        <CurrentNumber></CurrentNumber>
      </Player>
      <Player PlayerId="10">
        <Name>Kürşad Sürmeli</Name>
        <Fullname></Fullname>
        <Nickname></Nickname>
        <BirthDate>August 14, 1995</BirthDate>
        <BirthPlace City="Nijmegen" Country="Netherlands"/>
        <Height>1.73</Height>
        <Weight></Weight>
        <WikiPosition>Midfielder</WikiPosition>
        <GoalComPosition></GoalComPosition>
        <GoalComPlayerNumber>8</GoalComPlayerNumber>
        <GoalComShownName>K. Sürmeli</GoalComShownName>
        <GoalComWebsite>http://www.goal.com/en/people/netherlands/100811/k%C3%BCr%C5%9Fad-s%C3%BCrmeli</GoalComWebsite>
        <YouthClubs>
          <YouthClub YouthClubId="1" Years="">SV Hatert</YouthClub>
          <YouthClub YouthClubId="2" Years="">Quick 1888</YouthClub>
          <YouthClub YouthClubId="3" Years="2008-2012">N.E.C.</YouthClub>
        </YouthClubs>
        <SeniorClubs>
          <SeniorClub SeniorClubId="1" Years="2012-2013" Caps="" Goals="">Sportclub N.E.C.</SeniorClub>
          <SeniorClub SeniorClubId="2" Years="2013-" Caps="121" Goals="10">Achilles '29</SeniorClub>
        </SeniorClubs>
        <NationalTeams/>
        <CurrentTeam>Achilles '29</CurrentTeam>
        <CurrentNumber>8</CurrentNumber>
      </Player>
      <Player PlayerId="11">
        <Name>Freek Thoone</Name>
        <Fullname></Fullname>
        <Nickname></Nickname>
        <BirthDate>June 29, 1985</BirthDate>
        <BirthPlace City="Leunen" Country="Netherlands"/>
        <Height>1.79</Height>
        <Weight></Weight>
        <WikiPosition>Forward</WikiPosition>
        <GoalComPosition></GoalComPosition>
        <GoalComPlayerNumber>17</GoalComPlayerNumber>
        <GoalComShownName>F. Thoone</GoalComShownName>
        <GoalComWebsite>http://www.goal.com/en/people/netherlands/80440/freek-thoone</GoalComWebsite>
        <YouthClubs>
          <YouthClub YouthClubId="1" Years="">SV Leunen</YouthClub>
        </YouthClubs>
        <SeniorClubs>
          <SeniorClub SeniorClubId="1" Years="2002-2006" Caps="" Goals="">SV Leunen</SeniorClub>
          <SeniorClub SeniorClubId="2" Years="2006-2012" Caps="" Goals="">SV Venray</SeniorClub>
          <SeniorClub SeniorClubId="3" Years="2012-" Caps="149" Goals="43">Achilles '29</SeniorClub>
        </SeniorClubs>
        <NationalTeams/>
        <CurrentTeam>Achilles '29</CurrentTeam>
        <CurrentNumber>17</CurrentNumber>
      </Player>
    </Away>
  </Lineups>
  <Substitutes>
    <Home>
      <Substitute SubstituteId="1">
        <Name>Cor Varkevisser</Name>
        <Fullname>Cor Varkevisser</Fullname>
        <Nickname></Nickname>
        <BirthDate>May 14, 1982</BirthDate>
        <BirthPlace City="Leiden" Country="Netherlands"/>
        <Height>1.94</Height>
        <Weight></Weight>
        <WikiPosition>Goalkeeper</WikiPosition>
        <GoalComPosition></GoalComPosition>
        <GoalComPlayerNumber>1</GoalComPlayerNumber>
        <GoalComShownName>C. Varkevisser</GoalComShownName>
        <GoalComWebsite>http://www.goal.com/en/people/netherlands/16842/cor-varkevisser</GoalComWebsite>
        <YouthClubs>
          <YouthClub YouthClubId="1" Years="">Quick Boys</YouthClub>
          <YouthClub YouthClubId="2" Years="">Feyenoord</YouthClub>
        </YouthClubs>
        <SeniorClubs>
          <SeniorClub SeniorClubId="1" Years="2000-2001" Caps="0" Goals="0">Feyenoord</SeniorClub>
          <SeniorClub SeniorClubId="2" Years="2001-2005" Caps="70" Goals="0">Excelsior</SeniorClub>
          <SeniorClub SeniorClubId="3" Years="2005-2007" Caps="28" Goals="0">VVV-Venlo</SeniorClub>
          <SeniorClub SeniorClubId="4" Years="2007-2010" Caps="14" Goals="0">Sparta Rotterdam</SeniorClub>
          <SeniorClub SeniorClubId="5" Years="2010-2016" Caps="147" Goals="0">Telstar</SeniorClub>
          <SeniorClub SeniorClubId="6" Years="2016-" Caps="0" Goals="0">Quick Boys</SeniorClub>
        </SeniorClubs>
        <NationalTeams>
          <NationalTeam NationalTeamId="1" Years="" Caps="" Goals="">Netherlands U21</NationalTeam>
        </NationalTeams>
        <CurrentTeam>Quick Boys</CurrentTeam>
        <CurrentNumber>21</CurrentNumber>
      </Substitute>
      <Substitute SubstituteId="2">
        <Name>Tim Keurntjes</Name>
        <Fullname>Tim Keurntjes</Fullname>
        <Nickname></Nickname>
        <BirthDate>March 13, 1991</BirthDate>
        <BirthPlace City="Doetinchem" Country="Netherlands"/>
        <Height>1.76</Height>
        <Weight></Weight>
        <WikiPosition>Left back</WikiPosition>
        <GoalComPosition></GoalComPosition>
        <GoalComPlayerNumber>8</GoalComPlayerNumber>
        <GoalComShownName>T. Keurntjes</GoalComShownName>
        <GoalComWebsite>http://www.goal.com/en/people/netherlands/62104/tim-keurntjes</GoalComWebsite>
        <YouthClubs>
          <YouthClub YouthClubId="1" Years="2008-2010">De Graafschap</YouthClub>
        </YouthClubs>
        <SeniorClubs>
          <SeniorClub SeniorClubId="1" Years="2009-2010" Caps="3" Goals="0">De Graafschap</SeniorClub>
          <SeniorClub SeniorClubId="2" Years="2010-2013" Caps="8" Goals="0">FC Groningen</SeniorClub>
          <SeniorClub SeniorClubId="3" Years="2012-2013" Caps="13" Goals="0">→ SC Cambuur (loan)</SeniorClub>
          <SeniorClub SeniorClubId="4" Years="2013-2016" Caps="59" Goals="7">Telstar</SeniorClub>
          <SeniorClub SeniorClubId="5" Years="2016-" Caps="0" Goals="0">De Graafschap</SeniorClub>
        </SeniorClubs>
        <NationalTeams/>
        <CurrentTeam>De Graafschap</CurrentTeam>
        <CurrentNumber>22</CurrentNumber>
      </Substitute>
      <Substitute SubstituteId="3">
        <Name>Bryan Ottenhoff</Name>
        <Fullname></Fullname>
        <Nickname></Nickname>
        <BirthDate>July 08, 1991</BirthDate>
        <BirthPlace City="Amsterdam" Country="Netherlands"/>
        <Height>1.87</Height>
        <Weight></Weight>
        <WikiPosition>Centre back</WikiPosition>
        <GoalComPosition></GoalComPosition>
        <GoalComPlayerNumber>4</GoalComPlayerNumber>
        <GoalComShownName>B. Ottenhoff</GoalComShownName>
        <GoalComWebsite>http://www.goal.com/en/people/netherlands/89461/bryan-ottenhoff</GoalComWebsite>
        <YouthClubs>
          <YouthClub YouthClubId="1" Years="">Ajax</YouthClub>
          <YouthClub YouthClubId="2" Years="">VA FC Twente</YouthClub>
        </YouthClubs>
        <SeniorClubs>
          <SeniorClub SeniorClubId="1" Years="2013-2014" Caps="29" Goals="0">Almere City</SeniorClub>
          <SeniorClub SeniorClubId="2" Years="2014-2015" Caps="0" Goals="0">Oțelul Galați</SeniorClub>
          <SeniorClub SeniorClubId="3" Years="2015-" Caps="24" Goals="0">Telstar</SeniorClub>
        </SeniorClubs>
        <NationalTeams/>
        <CurrentTeam>Telstar</CurrentTeam>
        <CurrentNumber>4</CurrentNumber>
      </Substitute>
      <Substitute SubstituteId="4">
        <Name>Liban Abdulahi</Name>
        <Fullname></Fullname>
        <Nickname></Nickname>
        <BirthDate>November 02, 1995</BirthDate>
        <BirthPlace City="Haarlem" Country="Netherlands"/>
        <Height>1.78</Height>
        <Weight></Weight>
        <WikiPosition>Midfielder</WikiPosition>
        <GoalComPosition></GoalComPosition>
        <GoalComPlayerNumber>21</GoalComPlayerNumber>
        <GoalComShownName>L. Abdulahi</GoalComShownName>
        <GoalComWebsite>http://www.goal.com/en/people/netherlands/173272/liban-abdulahi</GoalComWebsite>
        <YouthClubs>
          <YouthClub YouthClubId="1" Years="">SV Hoofddorp</YouthClub>
          <YouthClub YouthClubId="2" Years="2009-2010">HFC Haarlem</YouthClub>
          <YouthClub YouthClubId="3" Years="2010-2011">AFC Ajax</YouthClub>
          <YouthClub YouthClubId="4" Years="2011-2012">A.V.V. Zeeburgia</YouthClub>
          <YouthClub YouthClubId="5" Years="2012-2014">FC Groningen</YouthClub>
        </YouthClubs>
        <SeniorClubs>
          <SeniorClub SeniorClubId="1" Years="2014-2015" Caps="0" Goals="0">FC Volendam</SeniorClub>
          <SeniorClub SeniorClubId="2" Years="2015-" Caps="40" Goals="4">SC Telstar</SeniorClub>
        </SeniorClubs>
        <NationalTeams/>
        <CurrentTeam>SC Telstar</CurrentTeam>
        <CurrentNumber>14</CurrentNumber>
      </Substitute>
      <Substitute SubstituteId="5">
        <Name>Tom Noordhoff</Name>
        <Fullname>Tom Noordhoff</Fullname>
        <Nickname></Nickname>
        <BirthDate>July 19, 1995</BirthDate>
        <BirthPlace City="Haarlem" Country="Netherlands"/>
        <Height>1.78</Height>
        <Weight></Weight>
        <WikiPosition>Defensive midfielder</WikiPosition>
        <GoalComPosition></GoalComPosition>
        <GoalComPlayerNumber>14</GoalComPlayerNumber>
        <GoalComShownName>T. Noordhoff</GoalComShownName>
        <GoalComWebsite>http://www.goal.com/en/people/netherlands/103298/tom-noordhoff</GoalComWebsite>
        <YouthClubs>
          <YouthClub YouthClubId="1" Years="">VV Schoten</YouthClub>
          <YouthClub YouthClubId="2" Years="-2007">Telstar</YouthClub>
          <YouthClub YouthClubId="3" Years="2007-2013">Ajax</YouthClub>
        </YouthClubs>
        <SeniorClubs>
          <SeniorClub SeniorClubId="1" Years="2013-2015" Caps="0" Goals="0">Ajax</SeniorClub>
          <SeniorClub SeniorClubId="2" Years="2013-2015" Caps="17" Goals="1">→ Jong Ajax</SeniorClub>
          <SeniorClub SeniorClubId="3" Years="2015-2016" Caps="7" Goals="0">Telstar</SeniorClub>
          <SeniorClub SeniorClubId="4" Years="2016-" Caps="0" Goals="0">Almere City</SeniorClub>
        </SeniorClubs>
        <NationalTeams>
          <NationalTeam NationalTeamId="1" Years="2011" Caps="3" Goals="0">Netherlands U17</NationalTeam>
          <NationalTeam NationalTeamId="2" Years="2013" Caps="1" Goals="0">Netherlands U18</NationalTeam>
        </NationalTeams>
        <CurrentTeam>Almere City</CurrentTeam>
        <CurrentNumber>23</CurrentNumber>
      </Substitute>
      <Substitute SubstituteId="6">
        <Name>Rafael Uiterloo</Name>
        <Fullname>Rafael Steve Uiterloo</Fullname>
        <Nickname></Nickname>
        <BirthDate>December 07, 1990</BirthDate>
        <BirthPlace City="Amsterdam" Country="Netherlands"/>
        <Height>1.81</Height>
        <Weight></Weight>
        <WikiPosition>Striker</WikiPosition>
        <GoalComPosition></GoalComPosition>
        <GoalComPlayerNumber>11</GoalComPlayerNumber>
        <GoalComShownName>R. Uiterloo</GoalComShownName>
        <GoalComWebsite>http://www.goal.com/en/people/netherlands/35294/rafael-uiterloo</GoalComWebsite>
        <YouthClubs>
          <YouthClub YouthClubId="1" Years="">SC Voorland</YouthClub>
          <YouthClub YouthClubId="2" Years="{{0|0000}}-2006">Zeeburgia</YouthClub>
          <YouthClub YouthClubId="3" Years="2006-2008">Ajax</YouthClub>
          <YouthClub YouthClubId="4" Years="2008-2010">Utrecht</YouthClub>
        </YouthClubs>
        <SeniorClubs>
          <SeniorClub SeniorClubId="1" Years="2008-2010" Caps="9" Goals="1">Utrecht</SeniorClub>
          <SeniorClub SeniorClubId="2" Years="2009" Caps="0" Goals="0">→ Omniworld (loan)</SeniorClub>
          <SeniorClub SeniorClubId="3" Years="2010-2011" Caps="1" Goals="0">Baniyas</SeniorClub>
          <SeniorClub SeniorClubId="4" Years="2013-2015" Caps="51" Goals="26">FC Lienden</SeniorClub>
          <SeniorClub SeniorClubId="5" Years="2015-2016" Caps="18" Goals="1">Telstar</SeniorClub>
          <SeniorClub SeniorClubId="6" Years="2016-" Caps="0" Goals="0">FC Eindhoven</SeniorClub>
        </SeniorClubs>
        <NationalTeams/>
        <CurrentTeam>FC Eindhoven</CurrentTeam>
        <CurrentNumber></CurrentNumber>
      </Substitute>
      <Substitute SubstituteId="7">
        <Name>شيت Schet</Name>
        <Fullname></Fullname>
        <Nickname></Nickname>
        <BirthDate>April 08, 1990</BirthDate>
        <BirthPlace City="" Country=""/>
        <Height></Height>
        <Weight></Weight>
        <WikiPosition>Forward</WikiPosition>
        <GoalComPosition></GoalComPosition>
        <GoalComPlayerNumber>25</GoalComPlayerNumber>
        <GoalComShownName>D. Schet</GoalComShownName>
        <GoalComWebsite>http://www.goal.com/en/people/netherlands/60226/%D8%B4%D9%8A%D8%AA-schet</GoalComWebsite>
        <YouthClubs/>
        <SeniorClubs/>
        <NationalTeams/>
        <CurrentTeam></CurrentTeam>
        <CurrentNumber></CurrentNumber>
      </Substitute>
    </Home>
    <Away>
      <Substitute SubstituteId="1">
        <Name>Simon Van Beers</Name>
        <Fullname></Fullname>
        <Nickname></Nickname>
        <BirthDate>June 02, 1994</BirthDate>
        <BirthPlace City="" Country=""/>
        <Height></Height>
        <Weight></Weight>
        <WikiPosition>Goalkeeper</WikiPosition>
        <GoalComPosition></GoalComPosition>
        <GoalComPlayerNumber>16</GoalComPlayerNumber>
        <GoalComShownName>S. van Beers</GoalComShownName>
        <GoalComWebsite>http://www.goal.com/en/people/netherlands/67790/simon-van-beers</GoalComWebsite>
        <YouthClubs/>
        <SeniorClubs/>
        <NationalTeams/>
        <CurrentTeam></CurrentTeam>
        <CurrentNumber></CurrentNumber>
      </Substitute>
      <Substitute SubstituteId="2">
        <Name>Jordi van Kerkhof</Name>
        <Fullname></Fullname>
        <Nickname></Nickname>
        <BirthDate>June 10, 1996</BirthDate>
        <BirthPlace City="" Country=""/>
        <Height></Height>
        <Weight></Weight>
        <WikiPosition>Defender</WikiPosition>
        <GoalComPosition></GoalComPosition>
        <GoalComPlayerNumber>6</GoalComPlayerNumber>
        <GoalComShownName>J. van Kerkhof</GoalComShownName>
        <GoalComWebsite>http://www.goal.com/en/people/netherlands/236792/jordi-van-kerkhof</GoalComWebsite>
        <YouthClubs/>
        <SeniorClubs/>
        <NationalTeams/>
        <CurrentTeam></CurrentTeam>
        <CurrentNumber></CurrentNumber>
      </Substitute>
      <Substitute SubstituteId="3">
        <Name>Nicky van de Groes</Name>
        <Fullname></Fullname>
        <Nickname></Nickname>
        <BirthDate>November 20, 1985</BirthDate>
        <BirthPlace City="" Country=""/>
        <Height></Height>
        <Weight></Weight>
        <WikiPosition>Midfielder</WikiPosition>
        <GoalComPosition></GoalComPosition>
        <GoalComPlayerNumber>20</GoalComPlayerNumber>
        <GoalComShownName>N. van de Groes</GoalComShownName>
        <GoalComWebsite>http://www.goal.com/en/people/netherlands/80441/nicky-van-de-groes</GoalComWebsite>
        <YouthClubs/>
        <SeniorClubs/>
        <NationalTeams/>
        <CurrentTeam></CurrentTeam>
        <CurrentNumber></CurrentNumber>
      </Substitute>
      <Substitute SubstituteId="4">
        <Name>Omid Popalzay</Name>
        <Fullname>Omid Popalzay</Fullname>
        <Nickname></Nickname>
        <BirthDate>January 25, 1996</BirthDate>
        <BirthPlace City="Kabul" Country="Afghanistan"/>
        <Height></Height>
        <Weight></Weight>
        <WikiPosition>Midfielder, Winger</WikiPosition>
        <GoalComPosition></GoalComPosition>
        <GoalComPlayerNumber>15</GoalComPlayerNumber>
        <GoalComShownName>Omid Popalzay</GoalComShownName>
        <GoalComWebsite>http://www.goal.com/en/people/afghanistan/202252/omid-popalzay</GoalComWebsite>
        <YouthClubs>
          <YouthClub YouthClubId="1" Years="">SV Estria</YouthClub>
          <YouthClub YouthClubId="2" Years="nbsp;-2015">NEC</YouthClub>
        </YouthClubs>
        <SeniorClubs>
          <SeniorClub SeniorClubId="1" Years="2015-" Caps="31" Goals="5">Achilles '29</SeniorClub>
        </SeniorClubs>
        <NationalTeams>
          <NationalTeam NationalTeamId="1" Years="2015-" Caps="12" Goals="2">Afghanistan</NationalTeam>
        </NationalTeams>
        <CurrentTeam>Achilles '29</CurrentTeam>
        <CurrentNumber>15</CurrentNumber>
      </Substitute>
      <Substitute SubstituteId="5">
        <Name>Daniel van Straaten</Name>
        <Fullname></Fullname>
        <Nickname></Nickname>
        <BirthDate>July 25, 1985</BirthDate>
        <BirthPlace City="" Country=""/>
        <Height></Height>
        <Weight></Weight>
        <WikiPosition>Midfielder</WikiPosition>
        <GoalComPosition></GoalComPosition>
        <GoalComPlayerNumber>23</GoalComPlayerNumber>
        <GoalComShownName>D. van Straaten</GoalComShownName>
        <GoalComWebsite>http://www.goal.com/en/people/netherlands/46685/daniel-van-straaten</GoalComWebsite>
        <YouthClubs/>
        <SeniorClubs/>
        <NationalTeams/>
        <CurrentTeam></CurrentTeam>
        <CurrentNumber></CurrentNumber>
      </Substitute>
      <Substitute SubstituteId="6">
        <Name>Brian Boogers</Name>
        <Fullname></Fullname>
        <Nickname></Nickname>
        <BirthDate>August 03, 1991</BirthDate>
        <BirthPlace City="" Country=""/>
        <Height></Height>
        <Weight></Weight>
        <WikiPosition>Forward</WikiPosition>
        <GoalComPosition></GoalComPosition>
        <GoalComPlayerNumber>9</GoalComPlayerNumber>
        <GoalComShownName>B. Boogers</GoalComShownName>
        <GoalComWebsite>http://www.goal.com/en/people/netherlands/80612/brian-boogers</GoalComWebsite>
        <YouthClubs/>
        <SeniorClubs/>
        <NationalTeams/>
        <CurrentTeam></CurrentTeam>
        <CurrentNumber></CurrentNumber>
      </Substitute>
      <Substitute SubstituteId="7">
        <Name>Thijs Hendriks</Name>
        <Fullname>Thijs Hendriks</Fullname>
        <Nickname></Nickname>
        <BirthDate>February 05, 1985</BirthDate>
        <BirthPlace City="Malden" Country="Netherlands"/>
        <Height>1.80</Height>
        <Weight></Weight>
        <WikiPosition>Forward</WikiPosition>
        <GoalComPosition></GoalComPosition>
        <GoalComPlayerNumber>10</GoalComPlayerNumber>
        <GoalComShownName>T. Hendriks</GoalComShownName>
        <GoalComWebsite>http://www.goal.com/en/people/netherlands/4717/thijs-hendriks</GoalComWebsite>
        <YouthClubs/>
        <SeniorClubs>
          <SeniorClub SeniorClubId="1" Years="2004-2005" Caps="4" Goals="1">NEC</SeniorClub>
          <SeniorClub SeniorClubId="2" Years="2005-" Caps="184" Goals="59">Achilles '29</SeniorClub>
          <SeniorClub SeniorClubId="3" Years="2017-" Caps="2" Goals="0">→ SV Spakenburg (loan)</SeniorClub>
        </SeniorClubs>
        <NationalTeams/>
        <CurrentTeam>SV Spakenburg(on loan from Achilles '29)</CurrentTeam>
        <CurrentNumber>32</CurrentNumber>
      </Substitute>
    </Away>
  </Substitutes>
  <Managers>
    <Home>
      <Manager ManagerId="1">
        <Name>Michel Vonk</Name>
        <Fullname>Michel Vonk</Fullname>
        <Nickname></Nickname>
        <BirthDate>October 28, 1968</BirthDate>
        <BirthPlace City="Alkmaar" Country="Netherlands"/>
        <Height></Height>
        <Weight></Weight>
        <WikiPosition>Defender</WikiPosition>
        <GoalComShownName>M. Vonk</GoalComShownName>
        <GoalComWebsite>http://www.goal.com/en/people/netherlands/53698/michel-vonk</GoalComWebsite>
        <YouthClubs/>
        <SeniorClubs>
          <SeniorClub SeniorClubId="1" Years="1986-1991" Caps="111" Goals="8">AZ</SeniorClub>
          <SeniorClub SeniorClubId="2" Years="1991-1992" Caps="51" Goals="1">SVV Dordrecht</SeniorClub>
          <SeniorClub SeniorClubId="3" Years="1992-1995" Caps="91" Goals="3">Manchester City</SeniorClub>
          <SeniorClub SeniorClubId="4" Years="1995" Caps="5" Goals="1">Oldham Athletic</SeniorClub>
          <SeniorClub SeniorClubId="5" Years="1995-1998" Caps="37" Goals="2">Sheffield United</SeniorClub>
          <SeniorClub SeniorClubId="6" Years="1998-2001" Caps="47" Goals="0">MVV Maastricht</SeniorClub>
        </SeniorClubs>
        <NationalTeams/>
        <CurrentTeam></CurrentTeam>
      </Manager>
    </Home>
    <Away>
      <Manager ManagerId="1">
        <Name>Eric Meijers</Name>
        <Fullname>Eric Meijers</Fullname>
        <Nickname></Nickname>
        <BirthDate>August 06, 1963</BirthDate>
        <BirthPlace City="Nijmegen" Country="Netherlands"/>
        <Height></Height>
        <Weight></Weight>
        <WikiPosition>Manager/Coach</WikiPosition>
        <GoalComShownName>E. Meijers</GoalComShownName>
        <GoalComWebsite>http://www.goal.com/en/people/netherlands/63460/eric-meijers</GoalComWebsite>
        <YouthClubs/>
        <SeniorClubs>
          <SeniorClub SeniorClubId="1" Years="?-1983" Caps="" Goals="">NEC</SeniorClub>
          <SeniorClub SeniorClubId="2" Years="1983-1991" Caps="" Goals="">SV Hatert</SeniorClub>
        </SeniorClubs>
        <NationalTeams/>
        <CurrentTeam>Achilles '29 (head coach)</CurrentTeam>
      </Manager>
    </Away>
  </Managers>
  <LastFiveGames>
    <Home>
      <Match MatchId="1">
        <Opponent>PSV Eindhoven II</Opponent>
        <ResultGame CurrentTeamGoals="0" OpponentGoals="1">1-0</ResultGame>
        <HomeAwayGame>away</HomeAwayGame>
        <WinDrawLostGame>lost</WinDrawLostGame>
      </Match>
      <Match MatchId="2">
        <Opponent>FC Utrecht II</Opponent>
        <ResultGame CurrentTeamGoals="3" OpponentGoals="1">3-1</ResultGame>
        <HomeAwayGame>home</HomeAwayGame>
        <WinDrawLostGame>win</WinDrawLostGame>
      </Match>
      <Match MatchId="3">
        <Opponent>FC Dordrecht</Opponent>
        <ResultGame CurrentTeamGoals="2" OpponentGoals="0">0-2</ResultGame>
        <HomeAwayGame>away</HomeAwayGame>
        <WinDrawLostGame>win</WinDrawLostGame>
      </Match>
      <Match MatchId="4">
        <Opponent>SC Cambuur Leeuwarden</Opponent>
        <ResultGame CurrentTeamGoals="1" OpponentGoals="5">5-1</ResultGame>
        <HomeAwayGame>away</HomeAwayGame>
        <WinDrawLostGame>lost</WinDrawLostGame>
      </Match>
      <Match MatchId="5">
        <Opponent>AFC Ajax II</Opponent>
        <ResultGame CurrentTeamGoals="1" OpponentGoals="3">1-3</ResultGame>
        <HomeAwayGame>home</HomeAwayGame>
        <WinDrawLostGame>lost</WinDrawLostGame>
      </Match>
    </Home>
    <Away>
      <Match MatchId="1">
        <Opponent>BV De Graafschap</Opponent>
        <ResultGame CurrentTeamGoals="3" OpponentGoals="3">3-3</ResultGame>
        <HomeAwayGame>away</HomeAwayGame>
        <WinDrawLostGame>draw</WinDrawLostGame>
      </Match>
      <Match MatchId="2">
        <Opponent>FC Dordrecht</Opponent>
        <ResultGame CurrentTeamGoals="2" OpponentGoals="2">2-2</ResultGame>
        <HomeAwayGame>home</HomeAwayGame>
        <WinDrawLostGame>draw</WinDrawLostGame>
      </Match>
      <Match MatchId="3">
        <Opponent>FC Volendam</Opponent>
        <ResultGame CurrentTeamGoals="2" OpponentGoals="1">1-2</ResultGame>
        <HomeAwayGame>away</HomeAwayGame>
        <WinDrawLostGame>win</WinDrawLostGame>
      </Match>
      <Match MatchId="4">
        <Opponent>FC Den Bosch</Opponent>
        <ResultGame CurrentTeamGoals="2" OpponentGoals="1">2-1</ResultGame>
        <HomeAwayGame>home</HomeAwayGame>
        <WinDrawLostGame>win</WinDrawLostGame>
      </Match>
      <Match MatchId="5">
        <Opponent>FC Emmen</Opponent>
        <ResultGame CurrentTeamGoals="0" OpponentGoals="1">1-0</ResultGame>
        <HomeAwayGame>away</HomeAwayGame>
        <WinDrawLostGame>lost</WinDrawLostGame>
      </Match>
    </Away>
  </LastFiveGames>
  <PreviousMeetings>
    <HomeTeamWins>4</HomeTeamWins>
    <AwayTeamWins>0</AwayTeamWins>
    <Draws>1</Draws>
    <HomeTeamWinPrediction>0%</HomeTeamWinPrediction>
    <DrawPrediction>100%</DrawPrediction>
    <AwayTeamWinPrediction>0%</AwayTeamWinPrediction>
    <PreviousMeetingsResults>
      <Meeting MeetingId="1">
        <Date>February 10, 2017</Date>
        <HomeTeam>Telstar</HomeTeam>
        <AwayTeam>Achilles '29</AwayTeam>
        <Result HomeTeamGoals="1" AwayTeamGoals="1">1-1</Result>
      </Meeting>
      <Meeting MeetingId="2">
        <Date>September 16, 2016</Date>
        <HomeTeam>Achilles '29</HomeTeam>
        <AwayTeam>Telstar</AwayTeam>
        <Result HomeTeamGoals="1" AwayTeamGoals="2">1-2</Result>
      </Meeting>
      <Meeting MeetingId="3">
        <Date>April 01, 2016</Date>
        <HomeTeam>Achilles '29</HomeTeam>
        <AwayTeam>Telstar</AwayTeam>
        <Result HomeTeamGoals="1" AwayTeamGoals="3">1-3</Result>
      </Meeting>
      <Meeting MeetingId="4">
        <Date>October 23, 2015</Date>
        <HomeTeam>Telstar</HomeTeam>
        <AwayTeam>Achilles '29</AwayTeam>
        <Result HomeTeamGoals="3" AwayTeamGoals="0">3-0</Result>
      </Meeting>
      <Meeting MeetingId="5">
        <Date>March 02, 2015</Date>
        <HomeTeam>Achilles '29</HomeTeam>
        <AwayTeam>Telstar</AwayTeam>
        <Result HomeTeamGoals="1" AwayTeamGoals="3">1-3</Result>
      </Meeting>
    </PreviousMeetingsResults>
    <MostPredictedResults>
      <Prediction PredictionId="1">
        <PredictedResult HomeTeamGoals="0" AwayTeamGoals="0">0-0</PredictedResult>
      </Prediction>
    </MostPredictedResults>
  </PreviousMeetings>
  <Statistics>
    <Home>
      <TotalShots></TotalShots>
      <ShotsOnTarget></ShotsOnTarget>
      <CompletedPasses></CompletedPasses>
      <PassingAccuracy></PassingAccuracy>
      <Possession></Possession>
      <Corners></Corners>
      <Offsides></Offsides>
      <FoulsConceded></FoulsConceded>
      <TotalPasses></TotalPasses>
      <ShortPasses></ShortPasses>
      <LongPasses></LongPasses>
      <ForwardPasses></ForwardPasses>
      <BackPasses></BackPasses>
      <LeftPasses></LeftPasses>
      <RightPasses></RightPasses>
      <ForwardPassesPercentage></ForwardPassesPercentage>
      <BlockedShots></BlockedShots>
      <CentreShots></CentreShots>
      <LeftShots></LeftShots>
      <RightShots></RightShots>
      <OutsideArea></OutsideArea>
      <SuccessfulCrosses></SuccessfulCrosses>
      <TotalCrosses></TotalCrosses>
      <AccuracyCrosses></AccuracyCrosses>
      <CrossesInside18YardLine></CrossesInside18YardLine>
      <CrossesOutside18YardLine></CrossesOutside18YardLine>
      <LeftCrosses></LeftCrosses>
      <RightCrosses></RightCrosses>
      <TotalAttemptedTakeOns></TotalAttemptedTakeOns>
      <SuccessfulTakeOns></SuccessfulTakeOns>
      <SuccessfulFinal3rdTakeOns></SuccessfulFinal3rdTakeOns>
      <SuccessfulLeftSideFinal3rdTakeOns></SuccessfulLeftSideFinal3rdTakeOns>
      <SuccessfulCentreFinal3rdTakeOns></SuccessfulCentreFinal3rdTakeOns>
      <SuccessfulRightSideFinal3rdTakeOns></SuccessfulRightSideFinal3rdTakeOns>
      <Blocks></Blocks>
      <Interceptions></Interceptions>
      <Clearances></Clearances>
      <Recoveries></Recoveries>
      <SuccessfulTackles></SuccessfulTackles>
      <TotalTackles></TotalTackles>
      <TackleAccuracy></TackleAccuracy>
    </Home>
    <Away>
      <TotalShots></TotalShots>
      <ShotsOnTarget></ShotsOnTarget>
      <CompletedPasses></CompletedPasses>
      <PassingAccuracy></PassingAccuracy>
      <Possession></Possession>
      <Corners></Corners>
      <Offsides></Offsides>
      <FoulsConceded></FoulsConceded>
      <TotalPasses></TotalPasses>
      <ShortPasses></ShortPasses>
      <LongPasses></LongPasses>
      <ForwardPasses></ForwardPasses>
      <BackPasses></BackPasses>
      <LeftPasses></LeftPasses>
      <RightPasses></RightPasses>
      <ForwardPassesPercentage></ForwardPassesPercentage>
      <BlockedShots></BlockedShots>
      <CentreShots></CentreShots>
      <LeftShots></LeftShots>
      <RightShots></RightShots>
      <OutsideArea></OutsideArea>
      <SuccessfulCrosses></SuccessfulCrosses>
      <TotalCrosses></TotalCrosses>
      <AccuracyCrosses></AccuracyCrosses>
      <CrossesInside18YardLine></CrossesInside18YardLine>
      <CrossesOutside18YardLine></CrossesOutside18YardLine>
      <LeftCrosses></LeftCrosses>
      <RightCrosses></RightCrosses>
      <TotalAttemptedTakeOns></TotalAttemptedTakeOns>
      <SuccessfulTakeOns></SuccessfulTakeOns>
      <SuccessfulFinal3rdTakeOns></SuccessfulFinal3rdTakeOns>
      <SuccessfulLeftSideFinal3rdTakeOns></SuccessfulLeftSideFinal3rdTakeOns>
      <SuccessfulCentreFinal3rdTakeOns></SuccessfulCentreFinal3rdTakeOns>
      <SuccessfulRightSideFinal3rdTakeOns></SuccessfulRightSideFinal3rdTakeOns>
      <Blocks></Blocks>
      <Interceptions></Interceptions>
      <Clearances></Clearances>
      <Recoveries></Recoveries>
      <SuccessfulTackles></SuccessfulTackles>
      <TotalTackles></TotalTackles>
      <TackleAccuracy></TackleAccuracy>
    </Away>
  </Statistics>
</Goal>
